[
    {
        "title": "Leica iCON Robot 70",
        "image": "/images/home/leica-icon-robot-70.webp",
        "link": "/shop/totalstationen/leica-icon-robot-70"
    },
    {
        "title": "Leica iCON Robot 80",
        "image": "/images/home/leica-icon-robot-80.webp",
        "link": "/shop/totalstationen/leica-icon-robot-80"
    },
    {
        "title": "Leica iCB 70",
        "image": "/images/home/leica-icb-70.webp",
        "link": "/shop/totalstationen/leica-icb-70"
    },
    {
        "title": "Leica iCON GPS 70T",
        "image": "/images/home/leica-icon-gps-70.webp",
        "link": "/shop/gps/leica-icg-70t"
    },
    {
        "title": "Leica iCON CC200",
        "image": "/images/home/leica-icon-cc-200.webp",
        "link": "/shop/tablets/leica-cc200"
    },
    {
        "title": "Leica iCON CC80",
        "image": "/images/home/leica-icon-cc-80.webp",
        "link": "/shop/tablets/leica-cc80"
    },
    {
        "title": "Leica AP20 AutoPole",
        "image": "/images/home/leica-ap-20-autopole.webp",
        "link": "/shop/totalstationen/leica-ap20-autopole"
    },
    {
        "title": "Leica Rugby CLA-CTIVE",
        "image": "/images/home/leica-rugby-cla-ctive.webp",
        "link": "/shop/baulaser/leica-rugby-cla-ctive"
    },
    {
        "title": "Geomax 60DG",
        "image": "/images/home/geomax-60-dg.webp",
        "link": "/shop/baulaser/geomax-60dg"
    }
]
